{"name":"build-javascript","namedChunkGroups":{"polyfill":{"name":"polyfill","assets":[{"name":"webpack-runtime-12be8315f5fcb26a187f.js","size":4412},{"name":"polyfill-f99b5e249e73f0ec1149.js","size":85874}],"filteredAssets":0,"assetsSize":90286,"filteredAuxiliaryAssets":2,"auxiliaryAssetsSize":225841},"app":{"name":"app","assets":[{"name":"webpack-runtime-12be8315f5fcb26a187f.js","size":4412},{"name":"framework-2da6f3f3aee6c7d06dc5.js","size":129787},{"name":"app-299a5ac519a00768b198.js","size":55879}],"filteredAssets":0,"assetsSize":190078,"filteredAuxiliaryAssets":3,"auxiliaryAssetsSize":565446},"component---src-pages-404-js":{"name":"component---src-pages-404-js","assets":[{"name":"component---src-pages-404-js-4b87509ea149c2a47705.js","size":839}],"filteredAssets":0,"assetsSize":839,"filteredAuxiliaryAssets":1,"auxiliaryAssetsSize":2007},"component---src-pages-index-js":{"name":"component---src-pages-index-js","assets":[{"name":"styles.fd998f36b279ec7d70e8.css","size":24008},{"name":"a9a7754c-3175b7299d2256b09183.js","size":2389},{"name":"component---src-pages-index-js-4f87e0139e78ac86944a.js","size":203556}],"filteredAssets":0,"assetsSize":229953,"filteredAuxiliaryAssets":18,"auxiliaryAssetsSize":2731741}},"assetsByChunkName":{"polyfill":["webpack-runtime-12be8315f5fcb26a187f.js","polyfill-f99b5e249e73f0ec1149.js"],"app":["webpack-runtime-12be8315f5fcb26a187f.js","framework-2da6f3f3aee6c7d06dc5.js","app-299a5ac519a00768b198.js"],"component---src-pages-404-js":["component---src-pages-404-js-4b87509ea149c2a47705.js"],"component---src-pages-index-js":["styles.fd998f36b279ec7d70e8.css","a9a7754c-3175b7299d2256b09183.js","component---src-pages-index-js-4f87e0139e78ac86944a.js"]},"childAssetsByChunkName":{}}